{
  "last_cycle": "2026-06-30T11:07:19.459389+00:00",
  "trigger": "live_session_end",
  "stats": {
    "agreements": 1394,
    "disagreements": 966,
    "corrections_for_ppo": 964,
    "corrections_for_halim": 2,
    "complements": 0,
    "label_v2_events": 462,
    "legacy_mislabeled_skipped": 1984,
    "market_proved_ppo": 4,
    "market_proved_halim": 0,
    "log_path": "halim/data/coevolution/correction_log.jsonl"
  },
  "export": {
    "ok": true,
    "added": 597,
    "total": 597,
    "events": 5491,
    "rewritten": true
  },
  "cycles": 56,
  "dialogue_export": {
    "ok": true,
    "pairs": 5208,
    "dialogue_lines": 2604,
    "rewritten": true
  }
}